shrinkray/__init__.py
shrinkray/__main__.py
shrinkray/cli.py
shrinkray/formatting.py
shrinkray/history.py
shrinkray/problem.py
shrinkray/process.py
shrinkray/py.typed
shrinkray/reducer.py
shrinkray/state.py
shrinkray/tui.py
shrinkray/ui.py
shrinkray/validation.py
shrinkray/work.py
shrinkray/passes/__init__.py
shrinkray/passes/bytes.py
shrinkray/passes/clangdelta.py
shrinkray/passes/definitions.py
shrinkray/passes/genericlanguages.py
shrinkray/passes/json.py
shrinkray/passes/patching.py
shrinkray/passes/python.py
shrinkray/passes/sat.py
shrinkray/passes/sequences.py
shrinkray/subprocess/__init__.py
shrinkray/subprocess/client.py
shrinkray/subprocess/protocol.py
shrinkray/subprocess/worker.py
shrinkray-26.1.1.0.dist-info/licenses/LICENSE
shrinkray-26.1.1.0.dist-info/METADATA
shrinkray-26.1.1.0.dist-info/WHEEL
shrinkray-26.1.1.0.dist-info/entry_points.txt
shrinkray-26.1.1.0.dist-info/top_level.txt
shrinkray-26.1.1.0.dist-info/RECORD
