Metadata-Version: 2.4
Name: shrinkray
Version: 26.1.1.0
Summary: Shrink Ray
Author-email: "David R. MacIver" <david@drmaciver.com>
License: MIT
Project-URL: Homepage, https://github.com/DRMacIver/shrinkray
Project-URL: Repository, https://github.com/DRMacIver/shrinkray
Project-URL: Documentation, https://shrinkray.readthedocs.io
Project-URL: Changelog, https://github.com/DRMacIver/shrinkray/releases
Classifier: Development Status :: 4 - Beta
Requires-Python: >=3.12
License-File: LICENSE
Requires-Dist: click>=8.0.1
Requires-Dist: chardet>=5.2.0
Requires-Dist: trio>=0.28.0
Requires-Dist: textual>=0.47.0
Requires-Dist: textual-plotext>=0.2.0
Requires-Dist: humanize>=4.9.0
Requires-Dist: libcst>=1.1.0
Requires-Dist: exceptiongroup>=1.2.0
Requires-Dist: binaryornot>=0.4.4
Requires-Dist: black>=24.1.0
Provides-Extra: dev
Requires-Dist: coverage>=7.4.0; extra == "dev"
Requires-Dist: hypothesis>=6.92.1; extra == "dev"
Requires-Dist: hypothesmith>=0.3.1; extra == "dev"
Requires-Dist: pytest>=8.0.0; extra == "dev"
Requires-Dist: pytest-trio>=0.8.0; extra == "dev"
Requires-Dist: pytest-asyncio>=0.21.0; extra == "dev"
Requires-Dist: pytest-xdist>=3.5.0; extra == "dev"
Requires-Dist: pytest-cov>=4.1.0; extra == "dev"
Requires-Dist: syrupy>=5.0.0; extra == "dev"
Requires-Dist: jinja2>=3.0.0; extra == "dev"
Requires-Dist: coverage[toml]>=7.4.0; extra == "dev"
Requires-Dist: pygments>=2.17.0; extra == "dev"
Requires-Dist: basedpyright>=1.1.0; extra == "dev"
Requires-Dist: ruff>=0.1.0; extra == "dev"
Requires-Dist: pexpect>=4.9.0; extra == "dev"
Requires-Dist: pyte>=0.8.2; extra == "dev"
Dynamic: license-file
